odoo8_addon_purchase_order_webkit_with_notes-8.0.1.0.1-py2.7-nspkg.pth
odoo_addons/purchase_order_webkit_with_notes/__openerp__.py
odoo_addons/purchase_order_webkit_with_notes/purchase_report.xml
odoo_addons/purchase_order_webkit_with_notes/purchase_order.py
odoo_addons/purchase_order_webkit_with_notes/__init__.py
odoo_addons/purchase_order_webkit_with_notes/report/request_quotation.mako
odoo_addons/purchase_order_webkit_with_notes/report/purchase_order.mako
odoo_addons/purchase_order_webkit_with_notes/report/__init__.py
odoo_addons/purchase_order_webkit_with_notes/view/purchase_view.xml
odoo_addons/purchase_order_webkit_with_notes/i18n/purchase_order_webkit.pot
odoo_addons/purchase_order_webkit_with_notes/i18n/fr.po
odoo8_addon_purchase_order_webkit_with_notes-8.0.1.0.1.dist-info/top_level.txt
odoo8_addon_purchase_order_webkit_with_notes-8.0.1.0.1.dist-info/WHEEL
odoo8_addon_purchase_order_webkit_with_notes-8.0.1.0.1.dist-info/RECORD
odoo8_addon_purchase_order_webkit_with_notes-8.0.1.0.1.dist-info/metadata.json
odoo8_addon_purchase_order_webkit_with_notes-8.0.1.0.1.dist-info/DESCRIPTION.rst
odoo8_addon_purchase_order_webkit_with_notes-8.0.1.0.1.dist-info/METADATA
odoo8_addon_purchase_order_webkit_with_notes-8.0.1.0.1.dist-info/namespace_packages.txt
