Metadata-Version: 2.0
Name: odoo8-addon-purchase-order-webkit-with-notes
Version: 8.0.1.0.1
Summary: Purchase Order Report using Webkit Library and notes
Home-page: http://www.camptocamp.com
Author: UNKNOWN
Author-email: UNKNOWN
License: UNKNOWN
Platform: UNKNOWN
Requires-Dist: odoo (<9.0a,>=8.0a)
Requires-Dist: odoo8-addon-base-headers-webkit
Classifier: Programming Language :: Python :: 2.7
Classifier: Framework :: Odoo
